{
    "items": [
       {
            "link": "https://raw.githubusercontent.com/hidemyassbaby/leomonade/main/xml/menu/Live%20TV/Countries/Allchannels.json", 
            "summary": "All TV Channels in one list", 
            "type": "dir", 
            "thumbnail": "https://i.postimg.cc/VLPbTf1J/image.png", 
            "title": "All Channels"
        },
        {
            "link": "https://raw.githubusercontent.com/hidemyassbaby/leomonade/main/xml/menu/Live%20TV/Sport/allsport.json", 
            "summary": "All Sport Channels in one list", 
            "type": "dir", 
            "thumbnail": "https://i.postimg.cc/RCgXPs6K/image.png",
            "title": "Sport Channels"
        },
        {
            "link": "https://github.com/hidemyassbaby/leomonade/raw/main/xml/menu/Live%20TV/Countries/usa.json", 
            "summary": "USA TV Channels", 
            "type": "dir", 
            "thumbnail": "https://i.postimg.cc/pTQB7vPD/image.png", 
            "title": "USA TV Channels"
        },
        {
            "link": "https://github.com/hidemyassbaby/leomonade/raw/main/xml/menu/Live%20TV/Countries/uk.json", 
            "summary": "UK TV Channels", 
            "type": "dir", 
            "thumbnail": "https://i.postimg.cc/vT1Gbfzy/image.png", 
            "title": "UK TV Channels"
        },
        {
            "content": "season",
            "fanart": "",
            "imdb": "",
            "link": "http://i.mjh.nz/nz/kodi-tv.m3u8",
            "summary": "Freeview is New Zealand's free-to-air television platform. It is operated by a joint venture between the country's major free-to-air broadcasters – government-owned Television New Zealand and Radio New Zealand, government-subsidised Māori Television, and the American-owned Warner Bros. Discovery New Zealand. (Geo Blocked)",
            "thumbnail": "https://encrypted-tbn0.gstatic.com/images?q=tbn:ANd9GcS4Dm3FR0QWT65YpLZxpT9dUrKFX9wJCEzZKrmEBVJwnepzhxibkzi_2TA&s=10",
            "title": "[COLOR=white]Freeview NZ[/COLOR]",
            "type": "dir",
            "year": "2022"
        },
        {
            "link": "https://raw.githubusercontent.com/hidemyassbaby/leomonade/main/xml/menu/Live%20TV/Countries/australia%20freeview.json", 
            "summary": "Australia TV Channels", 
            "type": "dir", 
            "thumbnail": "https://i.postimg.cc/P56YHnQn/image.png", 
            "title": "Australia TV Channels"
        },
        {
            "content": "season",
            "fanart": "",
            "imdb": "",
            "link": "https://i.mjh.nz/Stirr/all.m3u8",
            "summary": "Stirr is an American ad-supported video streaming service owned by Sinclair Broadcast Group. The streaming service is available on the web and via apps for iOS, Android devices and various streaming TV devices, including Amazon Fire TV, Roku, Apple TV, Chromecast and Android TV. Stirr's slogan is, the new free TV.",
            "thumbnail": "https://1.bp.blogspot.com/-8_37eUwLxBQ/X4j5lmPqfZI/AAAAAAAAGUI/KUwXn6_O_gEpXx4wE8XZb_Lq21W4tbNMQCLcBGAsYHQ/w1200-h630-p-k-no-nu/blog-thumb.jpg",
            "title": "[COLOR=red][B]Stirr[/B][/COLOR]",
            "type": "dir",
            "year": "2022"
        },
        {
            "content": "season",
            "fanart": "",
            "imdb": "",
            "link": "https://i.mjh.nz/Plex/all.m3u8",
            "summary": "Enjoy 80+ live TV channels with Plex",
            "thumbnail": "https://i.postimg.cc/SN9Zfhzr/image.png",
            "title": "[COLOR=red][B]Plex Live TV[/B][/COLOR]",
            "type": "dir",
            "year": "2022"
        },
        {
            "content": "season",
            "fanart": "",
            "imdb": "",
            "link": "https://i.mjh.nz/PlutoTV/all.m3u8",
            "summary": "Pluto TV is an internet television service owned and operated by Paramount Streaming, a division of Paramount Global",
            "thumbnail": "https://i.postimg.cc/65SXytxf/image.png",
            "title": "[COLOR red][B]PlutoTV[/COLOR][/B]",
            "type": "dir",
            "year": "2022"
        },
        {
            "type": "dir",
            "title": "[COLOR red][B]Samsung TV Plus[/COLOR][/B]",
            "samsung_tv": "regions"
        }
           
    ]
}



